{
  "db":{
    "clients":[
      {"phone":"1111111","name":"client1"},
      {"phone":"2222222","name":"client2"}
    ],
    "cars":[
      {"model":"KIA Sportage","number":"М111ММ116"},
      {"model":"Lada 21115","number":"Н222НН16"}
    ],
    "drivers":[
      {"phone":"33333333","name":"driver1","car":{"model":"KIA Sportage","number":"М111ММ116"}},
      {"phone":"44444444","name":"driver2","car":{"model":"Lada 21115","number":"Н222НН16"}}
    ],
    "trips":[
      {
        "date":"2021-09-13", "client":{"phone":"1111111","name":"client1"},
        "driver":{"phone":"33333333","name":"driver1","car":{"model":"KIA Sportage","number":"М111ММ116"}}
      },
      {
        "date":"2021-09-13", "client":{"phone":"2222222","name":"client2"},
        "driver":{"phone":"44444444","name":"driver2","car":{"model":"Lada 21115","number":"Н222НН16"}}
      }
    ]
  }
}